lazystream/__init__.py
lazystream-0.1.6.dist-info/LICENSE
lazystream-0.1.6.dist-info/METADATA
lazystream-0.1.6.dist-info/WHEEL
lazystream-0.1.6.dist-info/RECORD
