Metadata-Version: 2.1
Name: lazystream
Version: 0.1.6
Summary: Scala-inspired stream for lazy evaluation
Home-page: https://github.com/FizzyAgent/lazystream
License: MIT
Keywords: stream,lazy,functional
Author: Tan Pinxi
Author-email: tpinxi@gmail.com
Requires-Python: >=3.7,<4.0
Classifier: Development Status :: 2 - Pre-Alpha
Classifier: Intended Audience :: Developers
Classifier: License :: OSI Approved :: MIT License
Classifier: Natural Language :: English
Classifier: Programming Language :: Python :: 3
Classifier: Programming Language :: Python :: 3.7
Classifier: Programming Language :: Python :: 3.8
Classifier: Programming Language :: Python :: 3.9
Classifier: Programming Language :: Python :: 3.10
Classifier: Programming Language :: Python :: 3.11
Classifier: Programming Language :: Python :: 3.12
Project-URL: Repository, https://github.com/FizzyAgent/lazystream
